LICENSE
README
ez_setup.py
setup.py
lib/MyghtyUtils.egg-info/PKG-INFO
lib/MyghtyUtils.egg-info/SOURCES.txt
lib/MyghtyUtils.egg-info/dependency_links.txt
lib/MyghtyUtils.egg-info/top_level.txt
lib/myghtyutils/__init__.py
lib/myghtyutils/buffer.py
lib/myghtyutils/container.py
lib/myghtyutils/session.py
lib/myghtyutils/synchronization.py
lib/myghtyutils/util.py
lib/myghtyutils/ext/__init__.py
lib/myghtyutils/ext/memcached.py
test/Container.py
test/LRUCache.py
test/SyncDict.py
test/testbase.py
