Metadata-Version: 1.0
Name: MyghtyUtils
Version: 0.52
Summary: Container and Utility Functions from the Myghty Template Framework
Home-page: http://www.myghty.org
Author: Mike Bayer
Author-email: mike@myghty.org
License: MIT License
Platform: UNKNOWN
Classifier: Development Status :: 4 - Beta
Classifier: Intended Audience :: Developers
Classifier: License :: OSI Approved :: MIT License
Classifier: Programming Language :: Python
